superscreen/__init__.py
superscreen/about.py
superscreen/distance.py
superscreen/fem.py
superscreen/fluxoid.py
superscreen/geometry.py
superscreen/io.py
superscreen/parameter.py
superscreen/solution.py
superscreen/testing.py
superscreen/units.py
superscreen/version.py
superscreen/visualization.py
superscreen/device/__init__.py
superscreen/device/device.py
superscreen/device/edge_mesh.py
superscreen/device/layer.py
superscreen/device/mesh.py
superscreen/device/polygon.py
superscreen/device/utils.py
superscreen/solver/__init__.py
superscreen/solver/solve.py
superscreen/solver/solve_film.py
superscreen/solver/utils.py
superscreen/sources/__init__.py
superscreen/sources/constant.py
superscreen/sources/current.py
superscreen/sources/dipole.py
superscreen/sources/vortex.py
superscreen/test/__init__.py
superscreen/test/conftest.py
superscreen/test/test_about.py
superscreen/test/test_device.py
superscreen/test/test_distance.py
superscreen/test/test_parameter.py
superscreen/test/test_polygon.py
superscreen/test/test_solution.py
superscreen/test/test_solve.py
superscreen/test/test_sources.py
superscreen/test/test_transport.py
superscreen/test/test_visualization.py
superscreen-0.12.2.dist-info/licenses/LICENSE
superscreen-0.12.2.dist-info/METADATA
superscreen-0.12.2.dist-info/WHEEL
superscreen-0.12.2.dist-info/top_level.txt
superscreen-0.12.2.dist-info/RECORD
