Metadata-Version: 2.4
Name: superscreen
Version: 0.12.2
Summary: SuperScreen: simulate Meissner screening in 2D superconducting devices.
Home-page: https://github.com/loganbvh/superscreen
Author: Logan Bishop-Van Horn
Author-email: logan.bvh@gmail.com
License: MIT
Keywords: superconductor meissner screening
Platform: Linux
Platform: Mac OSX
Platform: Unix
Platform: Windows
Classifier: Development Status :: 4 - Beta
Classifier: Intended Audience :: Science/Research
Classifier: License :: OSI Approved :: MIT License
Classifier: Operating System :: MacOS
Classifier: Operating System :: POSIX
Classifier: Operating System :: Unix
Classifier: Operating System :: Microsoft :: Windows
Classifier: Programming Language :: Python
Classifier: Programming Language :: Python :: 3.8
Classifier: Programming Language :: Python :: 3.9
Classifier: Programming Language :: Python :: 3.10
Classifier: Programming Language :: Python :: 3.11
Classifier: Programming Language :: Python :: 3.12
Classifier: Programming Language :: Python :: 3.13
Classifier: Programming Language :: Python :: 3.14
Classifier: Topic :: Scientific/Engineering
Classifier: Topic :: Scientific/Engineering :: Physics
Requires-Python: >=3.8, <3.15
License-File: LICENSE
Requires-Dist: dill
Requires-Dist: h5py
Requires-Dist: ipython
Requires-Dist: joblib
Requires-Dist: jupyter
Requires-Dist: matplotlib
Requires-Dist: meshpy
Requires-Dist: numba
Requires-Dist: numpy
Requires-Dist: pint
Requires-Dist: pytest
Requires-Dist: scipy
Requires-Dist: shapely
Requires-Dist: tqdm
Provides-Extra: dev
Requires-Dist: pytest-cov; extra == "dev"
Requires-Dist: pre-commit; extra == "dev"
Provides-Extra: docs
Requires-Dist: sphinx<7; extra == "docs"
Requires-Dist: sphinx_rtd_theme; extra == "docs"
Requires-Dist: sphinx-autodoc-typehints; extra == "docs"
Requires-Dist: nbsphinx; extra == "docs"
Requires-Dist: pillow; extra == "docs"
Dynamic: author
Dynamic: author-email
Dynamic: classifier
Dynamic: description
Dynamic: description-content-type
Dynamic: home-page
Dynamic: keywords
Dynamic: license
Dynamic: license-file
Dynamic: platform
Dynamic: provides-extra
Dynamic: requires-dist
Dynamic: requires-python
Dynamic: summary
